spokennumbers/__init__.py
spokennumbers/__main__.py
spokennumbers/_info.py
spokennumbers/default/0.wav
spokennumbers/default/1.wav
spokennumbers/default/2.wav
spokennumbers/default/3.wav
spokennumbers/default/4.wav
spokennumbers/default/5.wav
spokennumbers/default/6.wav
spokennumbers/default/7.wav
spokennumbers/default/8.wav
spokennumbers/default/9.wav
spokennumbers/default/a.wav
spokennumbers/default/b.wav
spokennumbers/default/c.wav
spokennumbers-1.0.0.dist-info/LICENSE
spokennumbers-1.0.0.dist-info/METADATA
spokennumbers-1.0.0.dist-info/WHEEL
spokennumbers-1.0.0.dist-info/entry_points.txt
spokennumbers-1.0.0.dist-info/top_level.txt
spokennumbers-1.0.0.dist-info/RECORD
