Metadata-Version: 2.1
Name: spokennumbers
Version: 1.0.0
Summary: Generate spoken numbers mp3 files used for Memory Competitions
Home-page: https://github.com/Penlect/spokennumbers
Author: Daniel Andersson
Author-email: daniel.4ndersson@gmail.com
License: MIT
Keywords: spoken numbers iam wmc memory competition memorization
Platform: UNKNOWN
Classifier: Development Status :: 5 - Production/Stable
Classifier: Environment :: Console
Classifier: Intended Audience :: Developers
Classifier: Intended Audience :: Education
Classifier: Intended Audience :: Science/Research
Classifier: Topic :: Software Development :: Version Control :: Git
Classifier: License :: OSI Approved :: MIT License
Classifier: Natural Language :: English
Classifier: Operating System :: Microsoft :: Windows :: Windows 10
Classifier: Operating System :: POSIX :: Linux
Classifier: Programming Language :: Python :: 3.6
Classifier: Programming Language :: Python :: 3.7
Classifier: Programming Language :: Python :: 3.8
Classifier: Programming Language :: Python :: Implementation :: CPython
Requires-Dist: pydub
